[
    {
        "user_name": "vantan",
        "password": "abcdefgh",
        "address": "Ha Noi",
        "is_male": "true",
        "is_admin": "true",
        "email": "abcd@gmail.com"
    },
    {
        "user_name": "userdefault1",
        "password": "12345678",
        "address": "Ha Noi",
        "is_male": "false",
        "is_admin": "false",
        "email": "userdefault1@gmail.com"
    },
    {
        "user_name": "userdefault2",
        "password": "12345678",
        "address": "Ho Chi Minh",
        "is_male": "false",
        "is_admin": "false",
        "email": "userdefault2@gmail.com"
    }
]